bin_tree/__init__.py
bin_tree/avl_tree.py
bin_tree/bin_tree.py
bin_tree/red_black_tree.py
bin_tree/version.py
test/__init__.py
test/test_avl_tree.py
test/test_bin_tree.py
bin_tree-0.3.0.dist-info/LICENSE.txt
bin_tree-0.3.0.dist-info/METADATA
bin_tree-0.3.0.dist-info/WHEEL
bin_tree-0.3.0.dist-info/top_level.txt
bin_tree-0.3.0.dist-info/RECORD
