Metadata-Version: 2.1
Name: bin-tree
Version: 0.3.0
Summary: A python module that provides mutable mappings and sets implemented with binary trees.
Home-page: https://github.com/s-ball/bin_tree
Author: SBA
Author-email: s-ball@laposte.net
License: MIT License
Project-URL: Changelog, https://github.com/s-ball/bin_tree/blob/master/CHANGES.txt
Platform: UNKNOWN
Classifier: Development Status :: 4 - Beta
Classifier: Programming Language :: Python :: 3
Classifier: Programming Language :: Python :: 3.5
Classifier: Programming Language :: Python :: 3.6
Classifier: Programming Language :: Python :: 3.7
Classifier: Programming Language :: Python :: 3.8
Classifier: Intended Audience :: Developers
Classifier: License :: OSI Approved :: MIT License
Classifier: Operating System :: OS Independent
Requires-Python: >=3.5
